<?xml version="1.0" encoding="UTF-8"?>
<ConnList sysname="Charging"><item type="conn" code="A12"><note></note><partNo>90980-09213</partNo></item><item type="conn" code="A13"><note></note><partNo>90980-11349</partNo></item><item type="conn" code="A14"><note></note><partNo>90980-11556</partNo></item><item type="conn" code="A15"><note></note><partNo>90980-11469</partNo></item><item type="conn" code="B 6"><note></note><partNo>90980-11971</partNo></item><item type="conn" code="C10"><note></note><partNo>90980-11915</partNo></item><item type="conn" code="D 2"><note></note><partNo>90980-10803</partNo></item><item type="conn" code="E 2"><note></note><partNo>90980-11638</partNo></item><item type="conn" code="E 3"><note></note><partNo>90980-11637</partNo></item><item type="conn" code="E 6"><note></note><partNo>90980-11421</partNo></item><item type="conn" code="J 2"><note></note><partNo>90980-11661</partNo></item><item type="conn" code="J 3"><note></note><partNo>90980-11661</partNo></item><item type="conn" code="T 5"><note></note><partNo>90980-11424</partNo></item></ConnList>
